[
    {
        "index": 1,
        "imgSrc": "https://cmangag.com/assets/tmp/album/48549.png?v=1705382676",
        "name": "Hoá Ra Ta Đã Vô Địch Từ Lâu",
        "chapter": "Chapter 235",
        "viewers": "13"
    },
    {
        "index": 2,
        "imgSrc": "https://i.ytimg.com/vi/_8al4KfAILk/maxresdefault.jpg",
        "name": "Ta Có 90 Tỷ Tiền Liếm Cẩu!",
        "chapter": "Chapter 483",
        "viewers": "138k"
    },
    {
        "index": 3,
        "imgSrc": "https://encrypted-tbn0.gstatic.com/images?q=tbn:ANd9GcS5WJQgqtA7N7U3IiU3RGJZmARQ36YN6EkqaA&s",
        "name": "Ngã Lão Ma Thần",
        "chapter": "Chapter 243",
        "viewers": "5M"
    },
    {
        "index": 4,
        "imgSrc": "https://encrypted-tbn0.gstatic.com/images?q=tbn:ANd9GcQ0IYbJZPo__XD5CkXoZfsFvO6-HtqsUApvXw&s",
        "name": "Võ Luyện Đỉnh Phong",
        "chapter": "Chapter 3814",
        "viewers": "100M"
    },
    {
        "index": 5,
        "imgSrc": "https://encrypted-tbn0.gstatic.com/images?q=tbn:ANd9GcR1WS47aEYk5CaDCmvQypJzEeM9XBaMOgGNgA&s",
        "name": "Chính Nghĩa Không!! Ta Trở Thành phản diện",
        "chapter": "Chapter 109",
        "viewers": "3"
    }
]
